gw_sys_api_accessrights/__init__.py
gw_sys_api_accessrights/clients.py
gw_sys_api_accessrights-0.0.0.0.3.dist-info/LICENSE
gw_sys_api_accessrights-0.0.0.0.3.dist-info/METADATA
gw_sys_api_accessrights-0.0.0.0.3.dist-info/WHEEL
gw_sys_api_accessrights-0.0.0.0.3.dist-info/top_level.txt
gw_sys_api_accessrights-0.0.0.0.3.dist-info/RECORD
