Metadata-Version: 2.1
Name: gw-sys-api-accessrights
Version: 0.0.0.0.3
Summary: gw-sys-api-accessrights
Home-page: https://github.com/KeyisB/libs/tree/main/gw-sys-api-accessrights
Author: KeyisB
Author-email: keyisb.pip@gmail.com
License: MMB License v1.0
Classifier: Programming Language :: Python :: 3
Classifier: Operating System :: OS Independent
Requires-Python: >=3.12
License-File: LICENSE
Requires-Dist: KeyisBClient
